mdinfo_macos/__init__.py
mdinfo_macos/_version.py
mdinfo_macos/datetime_formatter.py
mdinfo_macos/help.py
mdinfo_macos/mdinfo_finder.py
mdinfo_macos/mdinfo_mac.py
mdinfo_macos-0.1.0.dist-info/LICENSE
mdinfo_macos-0.1.0.dist-info/METADATA
mdinfo_macos-0.1.0.dist-info/WHEEL
mdinfo_macos-0.1.0.dist-info/entry_points.txt
mdinfo_macos-0.1.0.dist-info/top_level.txt
mdinfo_macos-0.1.0.dist-info/RECORD
